Workbook

Sheet Assumptions
A1: ASSUMPTIONS & INPUTS — edit the shaded cells; everything else recalculates
A2: Yubi vs M2P · Bhawana Finance LMS · €100M/yr portfolio (annual disbursal)
A4: GLOBAL INPUTS (editable)
A5: FX rate — INR per €1 | B5: 90 | C5: Your booking/hedge rate. Template used 100. Drives every € figure.
A6: Annual disbursal (€) | B6: 100000000 | C6: €100M/yr = total disbursed per year (the agreed portfolio basis).
A7: Annual disbursal (₹) | B7: =B6*B5 | C7: Auto = annual disbursal € × FX.
A8: Average loan tenor (months) | B8: 6 | C8: Agreed 3–6 mo. Bridges disbursal→AUM for M2P. Try 3 and 6.
A9: Avg outstanding factor (book ÷ principal) | B9: 1 | C9: 1.0 = bullet (principal on book full tenor). ~0.55 = amortising EMI book.
A10: Number of LSPs / partners live | B10: 3 | C10: Yubi: first 3 free. M2P floor jumps to ₹4L once >1 LSP.
A11: Yubi free LSPs (no partnership fee) | B11: 3 | C11: Yubi waives partnership fee for the first 3 LSPs.
A12: Time horizon (years) | B12: 3 | C12: Drives 3-year TCO. M2P has a 36-month lock-in.
A13: Include M2P one-time in totals? (1=yes / 0=no) | B13: 1 | C13: M2P ₹55L is stated 'Paid by Meesho' (LSP). 0 = Bhawana-net view.
A14: Yubi change-request man-days (Year 1) | B14: 0 | C14: ₹20,000/man-day. Optional; default 0 (billed on actuals).
A15: M2P customization man-days (Year 1) | B15: 0 | C15: ₹17,000/man-day. Optional; default 0 (billed on actuals).
A17: DERIVED VALUES (auto-calculated)
A18: Monthly disbursal (€) | B18: =B6/12 | C18: =annual ÷ 12.
A19: Monthly disbursal (₹) | B19: =B7/12 | C19: =annual ÷ 12.
A20: Average AUM / book (€) | B20: =B6*(B8/12)*B9 | C20: =disbursal × (tenor/12) × outstanding factor.
A21: Average AUM / book (₹) | B21: =B7*(B8/12)*B9 | C21: =disbursal × (tenor/12) × outstanding factor.
A22: Average AUM (₹ Cr) | B22: =B21/10000000 | C22: Used for M2P fill-a-tier SaaS (1 Cr = ₹10,000,000).
A23: M2P monthly minimum floor (₹) | B23: =IF(B10>1,400000,150000) | C23: ₹4L multi-LSP / ₹1.5L Meesho-only, whichever > computed SaaS.

Sheet Vendor A - Yubi
A1: VENDOR A — YUBI (CredAvenue Pvt Ltd) · LMS Commercial · dated 15-Jun-2026
A3: Fee item | B3: Frequency / basis | C3: Amount (₹) | D3: Amount (€) | E3: Notes
A4: ONE-TIME FEES (paid by Bhawana Finance)
A5: Onboarding / system integration | B5: one-time | C5: 5000000 | D5: =C5/Assumptions!$B$5 | E5: ₹75L list price − ₹25L flat discount. Invoiced on finalisation.
A6: Yu – Reporting fee | B6: one-time | C6: 1500000 | D6: =C6/Assumptions!$B$5 | E6: Valid for the entire association. Invoiced with onboarding.
A7: Alert Management fee | B7: one-time | C7: 1000000 | D7: =C7/Assumptions!$B$5 | E7: Valid for the entire association. Invoiced with onboarding.
A8: Partnership fee (LSPs beyond free tier) | B8: one-time per LSP > 3 | C8: =500000*MAX(0,Assumptions!$B$10-Assumptions!$B$11) | D8: =C8/Assumptions!$B$5 | E8: First 3 LSPs waived; ₹5L per LSP thereafter, at each go-live.
A9: Subtotal — one-time | C9: =SUM(C5:C8) | D9: =C9/Assumptions!$B$5
A11: RECURRING FEES (per year)
A12: Annual Maintenance Fee (AMC) | B12: per year | C12: 1000000 | D12: =C12/Assumptions!$B$5 | E12: Year-1 invoiced upfront with onboarding; then annually.
A13: Platform fee — 0.20% of disbursal | B13: per year | C13: =0.002*Assumptions!$B$7 | D13: =C13/Assumptions!$B$5 | E13: 0.20%/mo on monthly disbursals = 0.20% × annual disbursal. Tenor-independent.
A14: Subtotal — recurring / year | C14: =SUM(C12:C13) | D14: =C14/Assumptions!$B$5
A16: VARIABLE / BILLED ON ACTUALS (excluded from totals unless man-days entered)
A17: AA / other 3rd-party API billing | B17: on actuals | C17: Pass-through | D17: Pass-through | E17: Excluded — depends on consumption.
A18: Change-request development | B18: ₹20,000 / man-day | C18: =20000*Assumptions!$B$14 | D18: =C18/Assumptions!$B$5 | E18: Year-1 estimate from man-days input. 8-hr day per resource.
A20: TOTALS
A21: YEAR 1 (one-time + recurring + CR) | B21: Year 1 | C21: =C9+C14+C18 | D21: =C21/Assumptions!$B$5
A22: Year 2 (recurring) | B22: Year 2 | C22: =C14 | D22: =C22/Assumptions!$B$5
A23: Year 3 (recurring) | B23: Year 3 | C23: =C14 | D23: =C23/Assumptions!$B$5
A24: 3-YEAR TCO | B24: =horizon | C24: =C9+C14*Assumptions!$B$12+C18 | D24: =C24/Assumptions!$B$5 | E24: One-time + recurring × years (+ CR Yr1).

Sheet Vendor B - M2P
A1: VENDOR B — M2P FINTECH (Finflux) · LoS+BRE+LMS Commercial · dated 24-Jun-2026
A3: Fee item | B3: Frequency / basis | C3: Amount (₹) | D3: Amount (€) | E3: Notes
A4: ONE-TIME FEES
A5: Implementation (LoS + BRE + LMS setup) | B5: one-time @ LOI/PO | C5: 5500000 | D5: =C5/Assumptions!$B$5 | E5: Quote states 'Paid by Meesho' (the LSP), not Bhawana. 100% at LOI/PO.
A6: One-time counted in totals (toggle) | B6: toggle-applied | C6: =IF(Assumptions!$B$13=1,C5,0) | D6: =C6/Assumptions!$B$5 | E6: Set Assumptions 'Include M2P one-time' = 0 for the Bhawana-net view.
A8: MONTHLY SaaS FEE — fill-a-tier (marginal slabs) on average AUM
A9: AUM slab (₹ Cr) | B9: Marginal rate / month | C9: Monthly fee (₹) | D9: AUM in slab (₹ Cr) | E9: 1 Cr = ₹10,000,000
A10: First 250 | B10: 0.00025 | C10: =D10*10000000*B10 | D10: =MAX(0,MIN(Assumptions!$B$22,250))
A11: 250 – 750 | B11: 0.000225 | C11: =D11*10000000*B11 | D11: =MAX(0,MIN(Assumptions!$B$22,750)-250)
A12: 750 – 1,500 | B12: 0.000175 | C12: =D12*10000000*B12 | D12: =MAX(0,MIN(Assumptions!$B$22,1500)-750)
A13: 1,500 – 2,500 | B13: 0.000125 | C13: =D13*10000000*B13 | D13: =MAX(0,MIN(Assumptions!$B$22,2500)-1500)
A14: Above 2,500 | B14: 8.5e-05 | C14: =D14*10000000*B14 | D14: =MAX(0,Assumptions!$B$22-2500)
A15: Computed monthly SaaS | C15: =SUM(C10:C14) | D15: =SUM(D10:D14) | E15: Σ slab fees (total AUM in col D)
A16: Monthly minimum floor | B16: per month | C16: =Assumptions!$B$23 | E16: ₹4L multi-LSP / ₹1.5L Meesho-only.
A17: Monthly recurring fee (billed) | B17: per month | C17: =MAX(C15,C16) | D17: =C17/Assumptions!$B$5 | E17: Higher of computed SaaS vs floor.
A19: RECURRING FEES (per year)
A20: Annual SaaS / platform fee | B20: per year | C20: =12*C17 | D20: =C20/Assumptions!$B$5 | E20: =12 × monthly recurring fee above.
A21: Subtotal — recurring / year | C21: =C20 | D21: =C21/Assumptions!$B$5
A23: VARIABLE / BILLED ON ACTUALS (excluded unless entered)
A24: Customization / new reports | B24: ₹17,000 / man-day | C24: =17000*Assumptions!$B$15 | D24: =C24/Assumptions!$B$5 | E24: Anything beyond the standard pack. Year-1 estimate from man-days.
A25: SMS / cloud telephony | B25: on actuals | C25: Pass-through | D25: Pass-through | E25: Extra if opted, as applicable.
A27: TOTALS
A28: YEAR 1 (one-time + recurring + cust.) | B28: Year 1 | C28: =C6+C21+C24 | D28: =C28/Assumptions!$B$5
A29: Year 2 (recurring) | B29: Year 2 | C29: =C21 | D29: =C29/Assumptions!$B$5
A30: Year 3 (recurring) | B30: Year 3 | C30: =C21 | D30: =C30/Assumptions!$B$5
A31: 3-YEAR TCO | B31: =horizon | C31: =C6+C21*Assumptions!$B$12+C24 | D31: =C31/Assumptions!$B$5 | E31: Incl. one-time only if toggle=1. 36-mo lock-in.

Sheet Comparison
A1: VENDOR PRICING COMPARISON — Yubi (A) vs M2P (B) · €100M/yr disbursal
A3: HEADLINE (recalculates with your assumptions)
A4: Lower 3-year TCO | B4: =IF('Vendor A - Yubi'!$C$24<'Vendor B - M2P'!$C$31,"Yubi (Vendor A)","M2P (Vendor B)") | C4: 3-yr saving (₹) | D4: =ABS('Vendor A - Yubi'!$C$24-'Vendor B - M2P'!$C$31) | E4: =ABS('Vendor A - Yubi'!$D$24-'Vendor B - M2P'!$D$31)
A5: Lower Year-1 cost | B5: =IF('Vendor A - Yubi'!$C$21<'Vendor B - M2P'!$C$28,"Yubi (Vendor A)","M2P (Vendor B)") | C5: Yr-1 saving (₹) | D5: =ABS('Vendor A - Yubi'!$C$21-'Vendor B - M2P'!$C$28) | E5: =ABS('Vendor A - Yubi'!$D$21-'Vendor B - M2P'!$D$28)
A6: Key driver | B6: Yubi recurring = 0.20% of disbursal (flat, tenor-independent). M2P recurring scales with AUM/tenor. See Sensitivity tab.
A8: ALL FIGURES IN INR (₹)
A9: Line item | B9: Frequency | C9: Yubi (A) | D9: M2P (B) | E9: Lower
A10: Setup / one-time fees | B10: one-time | C10: ='Vendor A - Yubi'!$C$9 | D10: ='Vendor B - M2P'!$C$6 | E10: =IF(C10<D10,"A",IF(C10>D10,"B","="))
A11: Fixed annual fee (AMC) | B11: per year | C11: ='Vendor A - Yubi'!$C$12 | D11: 0 | E11: =IF(C11<D11,"A",IF(C11>D11,"B","="))
A12: Variable platform fee | B12: per month | C12: =0.002*Assumptions!$B$19 | D12: ='Vendor B - M2P'!$C$17 | E12: =IF(C12<D12,"A",IF(C12>D12,"B","="))
A13: Variable platform fee | B13: per year | C13: ='Vendor A - Yubi'!$C$13 | D13: ='Vendor B - M2P'!$C$21 | E13: =IF(C13<D13,"A",IF(C13>D13,"B","="))
A14: Recurring total / year | B14: per year | C14: ='Vendor A - Yubi'!$C$14 | D14: ='Vendor B - M2P'!$C$21 | E14: =IF(C14<D14,"A",IF(C14>D14,"B","="))
A15: Billed on actuals (excluded) | B15: Yubi: AA/3rd-party APIs + change requests @₹20k/man-day. M2P: SMS/telephony + customization @₹17k/man-day.
A16: YEAR 1 TOTAL INVESTMENT | B16: Year 1 | C16: ='Vendor A - Yubi'!$C$21 | D16: ='Vendor B - M2P'!$C$28 | E16: =IF(C16<D16,"A",IF(C16>D16,"B","="))
A17: 3-YEAR TCO | B17: horizon | C17: ='Vendor A - Yubi'!$C$24 | D17: ='Vendor B - M2P'!$C$31 | E17: =IF(C17<D17,"A",IF(C17>D17,"B","="))
A19: ALL FIGURES IN EUR (€)
A20: Line item | B20: Frequency | C20: Yubi (A) | D20: M2P (B) | E20: Lower
A21: Setup / one-time fees | B21: one-time | C21: ='Vendor A - Yubi'!$D$9 | D21: ='Vendor B - M2P'!$D$6 | E21: =IF(C21<D21,"A",IF(C21>D21,"B","="))
A22: Fixed annual fee (AMC) | B22: per year | C22: ='Vendor A - Yubi'!$D$12 | D22: 0 | E22: =IF(C22<D22,"A",IF(C22>D22,"B","="))
A23: Variable platform fee | B23: per month | C23: =0.002*Assumptions!$B$18 | D23: ='Vendor B - M2P'!$D$17 | E23: =IF(C23<D23,"A",IF(C23>D23,"B","="))
A24: Variable platform fee | B24: per year | C24: ='Vendor A - Yubi'!$D$13 | D24: ='Vendor B - M2P'!$D$21 | E24: =IF(C24<D24,"A",IF(C24>D24,"B","="))
A25: Recurring total / year | B25: per year | C25: ='Vendor A - Yubi'!$D$14 | D25: ='Vendor B - M2P'!$D$21 | E25: =IF(C25<D25,"A",IF(C25>D25,"B","="))
A26: Billed on actuals (excluded) | B26: Yubi: AA/3rd-party APIs + change requests @₹20k/man-day. M2P: SMS/telephony + customization @₹17k/man-day.
A27: YEAR 1 TOTAL INVESTMENT | B27: Year 1 | C27: ='Vendor A - Yubi'!$D$21 | D27: ='Vendor B - M2P'!$D$28 | E27: =IF(C27<D27,"A",IF(C27>D27,"B","="))
A28: 3-YEAR TCO | B28: horizon | C28: ='Vendor A - Yubi'!$D$24 | D28: ='Vendor B - M2P'!$D$31 | E28: =IF(C28<D28,"A",IF(C28>D28,"B","="))

Sheet Sensitivity
A1: SENSITIVITY — recurring cost vs loan tenor & book amortisation (€/yr)
A2: Yubi recurring is flat (0.20% of disbursal, tenor-independent). M2P recurring scales with AUM.
A4: Avg tenor (months) | B4: M2P — bullet (factor 1.0) | C4: M2P — amortising (factor 0.55) | D4: Yubi (flat) | E4: Lower (amort. case)
A5: 3 | B5: =12*MAX((MAX(0,MIN((Assumptions!$B$7*(3/12)*1.0/10000000),250))*10000000*0.000250+MAX(0,MIN((Assumptions!$B$7*(3/12)*1.0/10000000),750)-250)*10000000*0.000225+MAX(0,MIN((Assumptions!$B$7*(3/12)*1.0/10000000),1500)-750)*10000000*0.000175+MAX(0,MIN((Assumptions!$B$7*(3/12)*1.0/10000000),2500)-1500)*10000000*0.000125+MAX(0,(Assumptions!$B$7*(3/12)*1.0/10000000)-2500)*10000000*0.000085),Assumptions!$B$23)/Assumptions!$B$5 | C5: =12*MAX((MAX(0,MIN((Assumptions!$B$7*(3/12)*0.55/10000000),250))*10000000*0.000250+MAX(0,MIN((Assumptions!$B$7*(3/12)*0.55/10000000),750)-250)*10000000*0.000225+MAX(0,MIN((Assumptions!$B$7*(3/12)*0.55/10000000),1500)-750)*10000000*0.000175+MAX(0,MIN((Assumptions!$B$7*(3/12)*0.55/10000000),2500)-1500)*10000000*0.000125+MAX(0,(Assumptions!$B$7*(3/12)*0.55/10000000)-2500)*10000000*0.000085),Assumptions!$B$23)/Assumptions!$B$5 | D5: =0.002*Assumptions!$B$6 | E5: =IF(C5<D5,"M2P","Yubi")
A6: 6 | B6: =12*MAX((MAX(0,MIN((Assumptions!$B$7*(6/12)*1.0/10000000),250))*10000000*0.000250+MAX(0,MIN((Assumptions!$B$7*(6/12)*1.0/10000000),750)-250)*10000000*0.000225+MAX(0,MIN((Assumptions!$B$7*(6/12)*1.0/10000000),1500)-750)*10000000*0.000175+MAX(0,MIN((Assumptions!$B$7*(6/12)*1.0/10000000),2500)-1500)*10000000*0.000125+MAX(0,(Assumptions!$B$7*(6/12)*1.0/10000000)-2500)*10000000*0.000085),Assumptions!$B$23)/Assumptions!$B$5 | C6: =12*MAX((MAX(0,MIN((Assumptions!$B$7*(6/12)*0.55/10000000),250))*10000000*0.000250+MAX(0,MIN((Assumptions!$B$7*(6/12)*0.55/10000000),750)-250)*10000000*0.000225+MAX(0,MIN((Assumptions!$B$7*(6/12)*0.55/10000000),1500)-750)*10000000*0.000175+MAX(0,MIN((Assumptions!$B$7*(6/12)*0.55/10000000),2500)-1500)*10000000*0.000125+MAX(0,(Assumptions!$B$7*(6/12)*0.55/10000000)-2500)*10000000*0.000085),Assumptions!$B$23)/Assumptions!$B$5 | D6: =0.002*Assumptions!$B$6 | E6: =IF(C6<D6,"M2P","Yubi")
A7: 9 | B7: =12*MAX((MAX(0,MIN((Assumptions!$B$7*(9/12)*1.0/10000000),250))*10000000*0.000250+MAX(0,MIN((Assumptions!$B$7*(9/12)*1.0/10000000),750)-250)*10000000*0.000225+MAX(0,MIN((Assumptions!$B$7*(9/12)*1.0/10000000),1500)-750)*10000000*0.000175+MAX(0,MIN((Assumptions!$B$7*(9/12)*1.0/10000000),2500)-1500)*10000000*0.000125+MAX(0,(Assumptions!$B$7*(9/12)*1.0/10000000)-2500)*10000000*0.000085),Assumptions!$B$23)/Assumptions!$B$5 | C7: =12*MAX((MAX(0,MIN((Assumptions!$B$7*(9/12)*0.55/10000000),250))*10000000*0.000250+MAX(0,MIN((Assumptions!$B$7*(9/12)*0.55/10000000),750)-250)*10000000*0.000225+MAX(0,MIN((Assumptions!$B$7*(9/12)*0.55/10000000),1500)-750)*10000000*0.000175+MAX(0,MIN((Assumptions!$B$7*(9/12)*0.55/10000000),2500)-1500)*10000000*0.000125+MAX(0,(Assumptions!$B$7*(9/12)*0.55/10000000)-2500)*10000000*0.000085),Assumptions!$B$23)/Assumptions!$B$5 | D7: =0.002*Assumptions!$B$6 | E7: =IF(C7<D7,"M2P","Yubi")
A8: 12 | B8: =12*MAX((MAX(0,MIN((Assumptions!$B$7*(12/12)*1.0/10000000),250))*10000000*0.000250+MAX(0,MIN((Assumptions!$B$7*(12/12)*1.0/10000000),750)-250)*10000000*0.000225+MAX(0,MIN((Assumptions!$B$7*(12/12)*1.0/10000000),1500)-750)*10000000*0.000175+MAX(0,MIN((Assumptions!$B$7*(12/12)*1.0/10000000),2500)-1500)*10000000*0.000125+MAX(0,(Assumptions!$B$7*(12/12)*1.0/10000000)-2500)*10000000*0.000085),Assumptions!$B$23)/Assumptions!$B$5 | C8: =12*MAX((MAX(0,MIN((Assumptions!$B$7*(12/12)*0.55/10000000),250))*10000000*0.000250+MAX(0,MIN((Assumptions!$B$7*(12/12)*0.55/10000000),750)-250)*10000000*0.000225+MAX(0,MIN((Assumptions!$B$7*(12/12)*0.55/10000000),1500)-750)*10000000*0.000175+MAX(0,MIN((Assumptions!$B$7*(12/12)*0.55/10000000),2500)-1500)*10000000*0.000125+MAX(0,(Assumptions!$B$7*(12/12)*0.55/10000000)-2500)*10000000*0.000085),Assumptions!$B$23)/Assumptions!$B$5 | D8: =0.002*Assumptions!$B$6 | E8: =IF(C8<D8,"M2P","Yubi")
A10: Reads: at the agreed 3–6 mo tenor M2P's AUM-based recurring sits well below Yubi's flat €200k/yr; the gap narrows as tenor (and book) grows.

Sheet Scorecard (optional)
A1: QUALITATIVE SCORECARD (optional) — fill scores 1–5 in the shaded cells
A2: Pricing lives in the Comparison tab. This mirrors the scorecard template's weighted rollup for a fuller view.
A4: Criteria | B4: Weight | C4: Yubi (A) | D4: M2P (B) | E4: Notes / basis for score
A5: 1. Adherence to RFP Instructions | B5: 0.05 | C5: 3 | D5: 3
A6: 2. Company Information | B6: 0.05 | C6: 3 | D6: 3
A7: 3. Project Understanding | B7: 0.2 | C7: 3 | D7: 3
A8: 4. Requirements | B8: 0.3 | C8: 3 | D8: 3
A9: 5. Product Viability & History | B9: 0.05 | C9: 3 | D9: 3
A10: 6. Terms & Conditions | B10: 0.05 | C10: 3 | D10: 3
A11: 7. Vendor Software Demonstration | B11: 0.25 | C11: 3 | D11: 3
A12: 8. Fee Summary | B12: 0.05 | C12: 3 | D12: 3
A13: Weight check (must = 1.00) | B13: =SUM(B5:B12)
A14: WEIGHTED TOTAL SCORE | C14: =SUMPRODUCT(B5:B11,C5:C11) | D14: =SUMPRODUCT(B5:B11,D5:D11) | E14: Higher = better.
